<?xml version="1.0" encoding="UTF-8"?>
<comment version="3.0">
  <caption>Vertical shot of a white building under the clear sky</caption>
  <note>A vertical shot of a white building under the clear sky</note>
  <place/>
  <categories>
    <category value="vertical"/>
    <category value="white"/>
    <category value="building"/>
    <category value="architecture"/>
    <category value="background"/>
    <category value="construction"/>
    <category value="old"/>
    <category value="blue"/>
    <category value="city"/>
    <category value="sky"/>
    <category value="wall"/>
    <category value="structure"/>
    <category value="house"/>
    <category value="exterior"/>
    <category value="travel"/>
    <category value="urban"/>
    <category value="isolated"/>
    <category value="design"/>
    <category value="tower"/>
    <category value="day"/>
    <category value="outdoors"/>
    <category value="color"/>
    <category value="home"/>
    <category value="stone"/>
    <category value="people"/>
    <category value="landmark"/>
    <category value="business"/>
    <category value="europe"/>
    <category value="modern"/>
    <category value="texture"/>
    <category value="red"/>
    <category value="outdoor"/>
    <category value="view"/>
    <category value="wood"/>
    <category value="pattern"/>
    <category value="build"/>
    <category value="adult"/>
    <category value="black"/>
    <category value="abstract"/>
    <category value="brick"/>
    <category value="wooden"/>
    <category value="window"/>
    <category value="green"/>
    <category value="beautiful"/>
    <category value="metal"/>
    <category value="detail"/>
    <category value="photography"/>
    <category value="person"/>
    <category value="industry"/>
  </categories>
</comment>
